{
    "nomApp" : "app",
    "rutes" : [
        {
            "ruta" : "gallery",
            "icona" : "image",
            "texte": "Gallery"
        },
        {
            "ruta" : "pong",
            "icona" : "folder_open",
            "texte": "Pong Minigame"
        },
        {
            "ruta" : "language",
            "icona" : "",
            "texte": "Languages"
        },
        {
            "ruta" : "star",
            "icona" : "star",
            "texte": " "
        }
    ]
}